mpesa/__ init __.py
mpesa/access_token.py
mpesa/business_to_customer.py
mpesa/customer_to_business.py
mpesa/transaction_query.py
mpesa/utils.py
koros_python_payments-1.0.5.dist-info/METADATA
koros_python_payments-1.0.5.dist-info/WHEEL
koros_python_payments-1.0.5.dist-info/top_level.txt
koros_python_payments-1.0.5.dist-info/RECORD
